tucuxi/__init__.py
tucuxi/py.typed
tucuxi/s3.py
tucuxi/session.py
tucuxi/sqs.py
tucuxi-0.1.2.dist-info/LICENSE.rst
tucuxi-0.1.2.dist-info/WHEEL
tucuxi-0.1.2.dist-info/METADATA
tucuxi-0.1.2.dist-info/RECORD
