Metadata-Version: 2.1
Name: tucuxi
Version: 0.1.2
Summary: Tucuxi
Home-page: https://github.com/unj-inovacao/tucuxi/
License: MIT
Keywords: AWS,S3,SQS
Author: Luccas Quadros
Author-email: luccas.quadros@softplan.com.br
Requires-Python: >=3.6.1,<4.0.0
Classifier: License :: OSI Approved :: MIT License
Classifier: Programming Language :: Python :: 3
Classifier: Programming Language :: Python :: 3.7
Classifier: Programming Language :: Python :: 3.8
Requires-Dist: boltons (>=20.1.0,<21.0.0)
Requires-Dist: boto3 (>=1.12.26,<2.0.0)
Project-URL: Changelog, https://github.com/unj-inovacao/tucuxi/releases
Project-URL: Documentation, https://tucuxi.readthedocs.io/
Project-URL: Repository, https://github.com/unj-inovacao/tucuxi/
